flimsy/__init__.py
flimsy/_util.py
flimsy/config.py
flimsy/fixture.py
flimsy/handlers.py
flimsy/helper.py
flimsy/loader.py
flimsy/log.py
flimsy/main.py
flimsy/query.py
flimsy/result.py
flimsy/runner.py
flimsy/sandbox.py
flimsy/state.py
flimsy/suite.py
flimsy/terminal.py
flimsy/test.py
flimsy/uid.py
flimsy/wrappers.py
flimsy-0.1.0.dist-info/AUTHORS.rst
flimsy-0.1.0.dist-info/LICENSE
flimsy-0.1.0.dist-info/METADATA
flimsy-0.1.0.dist-info/WHEEL
flimsy-0.1.0.dist-info/entry_points.txt
flimsy-0.1.0.dist-info/top_level.txt
flimsy-0.1.0.dist-info/RECORD
